{
  "continuousPattern": {
    "amplitude": [
      {
        "time": 0,
        "value": 0
      },
      {
        "time": 5,
        "value": 0.9
      },
      {
        "time": 60,
        "value": 0.65
      },
      {
        "time": 200,
        "value": 0.45
      },
      {
        "time": 450,
        "value": 0.28
      },
      {
        "time": 750,
        "value": 0.14
      },
      {
        "time": 1100,
        "value": 0.05
      },
      {
        "time": 1400,
        "value": 0
      }
    ],
    "frequency": [
      {
        "time": 0,
        "value": 0.58
      },
      {
        "time": 5,
        "value": 0.55
      },
      {
        "time": 1400,
        "value": 0.52
      }
    ]
  },
  "discretePattern": [
    {
      "time": 0,
      "amplitude": 0.9,
      "frequency": 0.55
    }
  ],
  "name": "GuitarStrum",
  "description": "A bold attack that slowly decays over a long sustain like a plucked string, great for musical interactions or satisfying confirmation moments.",
  "tags": [
    "Bold",
    "Flexible",
    "Ramp",
    "Long"
  ],
  "duration": 1400
}
