{
  "line": [
    [
      {
        "x": 0,
        "y": 0
      },
      {
        "x": 0.651,
        "y": 0.813
      },
      {
        "x": 0.651,
        "y": 0
      }
    ],
    [
      {
        "x": 0,
        "y": 0
      },
      {
        "x": 0.65,
        "y": 0.7
      }
    ]
  ],
  "bar": [
    {
      "x": 0.013,
      "y1": 0.897,
      "y2": 0.209
    },
    {
      "x": 0.117,
      "y1": 0.897,
      "y2": 0.322
    },
    {
      "x": 0.253,
      "y1": 0.903,
      "y2": 0.484
    },
    {
      "x": 0.4,
      "y1": 0.903,
      "y2": 0.716
    },
    {
      "x": 0.546,
      "y1": 0.906,
      "y2": 0.803
    },
    {
      "x": 0.651,
      "y1": 0.906,
      "y2": 1
    }
  ]
}